{
    "config": {
        "key": [
            "contributor",
            "timestamp"
        ]
    },
    "topDef": {
        "type": "record",
        "properties": {
            "contributor": {
                "type": "contributor",
                "definition": "mobile_user"
            },
            "timestamp": {
                "type": "datetime"
            },
            "Happiness": {
                "type": "string"
            },
            "long": {
                "type": "double"
            },
            "lat": {
                "type": "double"
            }
        }
    }
}
